sitzungsdienst/__init__.py
sitzungsdienst/models/__init__.py
sitzungsdienst/models/court.py
sitzungsdienst/models/express.py
sitzungsdienst/regex.py
sitzungsdienst/sta.py
sitzungsdienst/utils.py
sitzungsdienst-2.3.4.dist-info/LICENSE
sitzungsdienst-2.3.4.dist-info/WHEEL
sitzungsdienst-2.3.4.dist-info/METADATA
sitzungsdienst-2.3.4.dist-info/RECORD
