Metadata-Version: 2.1
Name: sitzungsdienst
Version: 2.3.4
Summary: Handles weekly assignment PDFs as exported by "web.sta"
Home-page: https://digitalbuero.eu
License: GPL-3.0-only
Keywords: websta,legal
Author: Digitalbüro
Author-email: pypi@digitalbuero.eu
Maintainer: Martin Folkers
Maintainer-email: hello@twobrain.io
Requires-Python: >=3.10,<4.0
Classifier: Development Status :: 5 - Production/Stable
Classifier: Environment :: Console
Classifier: Environment :: Web Environment
Classifier: Intended Audience :: Developers
Classifier: Intended Audience :: Legal Industry
Classifier: License :: OSI Approved :: GNU General Public License v3 (GPLv3)
Classifier: Operating System :: OS Independent
Classifier: Programming Language :: Python :: 3
Classifier: Programming Language :: Python :: 3.10
Classifier: Programming Language :: Python :: 3.10
Classifier: Programming Language :: Python :: 3.11
Classifier: Topic :: Internet :: WWW/HTTP
Classifier: Topic :: Software Development :: Libraries :: Python Modules
Classifier: Topic :: Text Processing
Requires-Dist: ics (>=0.7,<0.8)
Requires-Dist: pypdf2 (==2.0.0)
Project-URL: Funding, https://donate.rsf.org
Project-URL: Issue Tracker, https://codeberg.org/digitalbuero/sitzungsdienst/issues
Project-URL: Repository, https://codeberg.org/digitalbuero/sitzungsdienst
